{
  "name": "Gazze",
  "type": "race",
  "img": "media/Species/Magpies.webp",
  "system": {
    "description": {
      "value": "<p><span class=\"fontstyle0\">Non c'è niente da fare: le gazze non possono tenere per sé i loro artigli. Avidi e vanitosi insieme, la tentazione dei beni materiali (soprattutto se belli, scintillanti e preziosi) è terribilmente forte. I più virtuosi cercano di controllare questo istinto in vari modi, costringendosi ad accettare lavori che li tengano il più lontano possibile dagli oggetti del desiderio, ma la stragrande maggioranza si abbandona a diventare ladri per il semplice desiderio di possedere oggetti stravaganti e meravigliosi. Le gazze sono collezioniste nate e hanno un grande occhio nel riconoscere cosa vale la pena prendere e cosa no, anche quando perdono la testa per cose che non hanno alcun valore reale se non essere belle. Silenziose nella fuga, astute nella contrattazione e abili nei borseggi, le gazze si sono ragionevolmente guadagnate una reputazione per la loro astuzia. Poche persone, infatti, si fidano di una Gazza, che spesso finisce per avere pochi amici. Ciononostante questi Corbei sono chiacchieroni e amanti del buon ambiente, sempre pronti a offrire un giro per le osterie ai loro compagni. <br style=\"font-variant-numeric:normal;font-variant-east-asian:normal;line-height:normal;text-align:-webkit-auto;text-size-adjust:auto\" /></span></p><p><span class=\"fontstyle0\"><em><strong>Incremento dei Punteggi di Caratteristica.</strong></em> </span><span class=\"fontstyle2\">Il tuo  </span><span class=\"fontstyle0\">Il punteggio di Intelligenza </span>aumenta di 2 e il tuo punteggio di  <span class=\"fontstyle0\">Destrezza </span>aumenta di 1.</p><p><span class=\"fontstyle0\"><em><strong>Età.</strong></em> </span>Un Corbei raggiunge la maturità intorno ai 14 anni <span class=\"fontstyle0\">ed è immediatamente considerato indipendente. Hanno una vita media di circa 60 anni.</span></p><p><span class=\"fontstyle0\"><em><strong>Velocità.</strong></em></span>La tua velocità base al suolo è di 20 piedi e la tua <span class=\"fontstyle0\">velocità di volo è di 9 metri.</span></p><p><span class=\"fontstyle0\"><em><strong>Taglia. </strong></em></span>Una gazza può raggiungere un'altezza compresa tra 1,1 metri <span class=\"fontstyle0\">e 1,3 metri e un peso compreso tra 20 e 40 kg.</span>  <span class=\"fontstyle2\">La tua taglia è Media.</span></p><p><span class=\"fontstyle0\"><em><strong>Piccola.</strong></em> </span><span class=\"fontstyle2\">Hai esperienza nel Abilità di inganno.</span></p><p><span class=\"fontstyle0\"><em><strong>Furtivo.</strong></em></span><span class=\"fontstyle2\">Puoi scegliere tra Furtività o Rapidità di mano. Acquisisci competenza con questa abilità.</span> </p><p><span class=\"fontstyle2\">@Compendium[historia-it.species-features-it.ZLta2Wjm3OsgNAk0]{Wings}</span></p><p><span class=\"fontstyle2\">@Compendium[historia-it.species-features-it.DO8bJUsTURvkwDVu]{Pecking}</span></p><p><span class=\"fontstyle2\">@Compendium[historia-it.species-features-it.9ALHHLuQoSWQRqN4]{Gambe prensili}</span></p><p><span class=\"fontstyle2\">@Compendium[historia-it.species-features-it.fWjnyGpnIsnivS8u]{Veloce Apprendimento}</span></p><p>@Compendium[historia-it.species-features-it.prA3mswGSrkS0JOP]{Grande memoria}</p><p><span class=\"fontstyle2\">@Compendium[historia-it.species-features-it.8zkCWIuMshrlUwIg]{Volo sfuggente}</span></p><p><span class=\"fontstyle3\"><em><strong>Istinto di famiglia, cattivo presagio (Onnivoro): </strong></em></span><span class=\"fontstyle4\">\"Posso prevedere il peggio in ogni situazione.\"</span></p><p><span class=\"fontstyle0\"><em><strong>Istinto di specie, cleptomane: </strong></em></span><span class=\"fontstyle2\">\"Prendo ciò che mi piace.\"</span></p>",
      "chat": ""
    },
    "source": {
      "custom": "",
      "book": "HCB",
      "page": "100",
      "license": "",
      "rules": "2014",
      "revision": 1
    },
    "advancement": [
      {
        "type": "AbilityScoreImprovement",
        "_id": "FmvnXGVzC4px2M4m",
        "configuration": {
          "points": 0,
          "fixed": {
            "str": 0,
            "dex": 1,
            "con": 0,
            "int": 2,
            "wis": 0,
            "cha": 0
          },
          "cap": 2,
          "locked": []
        },
        "value": {
          "type": "asi"
        },
        "level": 0,
        "title": "",
        "hint": ""
      },
      {
        "type": "Size",
        "_id": "pZApitZRR2yTxRHG",
        "configuration": {
          "sizes": [
            "med"
          ]
        },
        "level": 0,
        "value": {}
      },
      {
        "type": "Trait",
        "configuration": {
          "grants": [
            "languages:standard:common"
          ],
          "mode": "default",
          "allowReplacements": false,
          "choices": []
        },
        "_id": "U7DJteR1EUCfjO0q",
        "value": {
          "chosen": []
        },
        "level": 0
      },
      {
        "_id": "z5Heq9NOAwSKgwWV",
        "type": "Trait",
        "configuration": {
          "mode": "default",
          "allowReplacements": false,
          "grants": [
            "skills:dec"
          ],
          "choices": [
            {
              "count": 1,
              "pool": [
                "skills:slt",
                "skills:ste"
              ]
            }
          ]
        },
        "value": {
          "chosen": []
        },
        "level": 0,
        "title": "",
        "hint": ""
      },
      {
        "_id": "gjwOdMgr1osw6mUe",
        "type": "ItemGrant",
        "configuration": {
          "items": [
            {
              "uuid": "Compendium.historia-it.species-features-it.Item.ZLta2Wjm3OsgNAk0",
              "optional": false
            },
            {
              "uuid": "Compendium.historia-it.species-features-it.Item.DO8bJUsTURvkwDVu",
              "optional": false
            },
            {
              "uuid": "Compendium.historia-it.species-features-it.Item.9ALHHLuQoSWQRqN4",
              "optional": false
            },
            {
              "uuid": "Compendium.historia-it.species-features-it.Item.fWjnyGpnIsnivS8u",
              "optional": false
            },
            {
              "uuid": "Compendium.historia-it.species-features-it.Item.prA3mswGSrkS0JOP",
              "optional": false
            },
            {
              "uuid": "Compendium.historia-it.species-features-it.Item.8zkCWIuMshrlUwIg",
              "optional": false
            }
          ],
          "optional": false,
          "spell": null
        },
        "value": {},
        "level": 0
      }
    ],
    "movement": {
      "burrow": null,
      "climb": null,
      "fly": 30,
      "swim": null,
      "walk": 20,
      "units": null,
      "hover": false
    },
    "senses": {
      "darkvision": null,
      "blindsight": null,
      "tremorsense": null,
      "truesight": null,
      "units": null,
      "special": ""
    },
    "type": {
      "value": "custom",
      "custom": "Corbei",
      "subtype": ""
    },
    "identifier": "magpies"
  },
  "effects": [],
  "folder": null,
  "flags": {},
  "_stats": {
    "coreVersion": "12.331",
    "systemId": "dnd5e",
    "systemVersion": "5.2.5",
    "createdTime": 1738079481447,
    "modifiedTime": 1739535135157,
    "lastModifiedBy": "ZPF6iTR58NcfHa9O"
  },
  "_id": "GQfw4CfHGvDBqWWO"
}